{
  "title": "Power Consumption (Historical)",
  "uid": "power-historical",
  "description": "Long-term historical power monitoring from VictoriaMetrics. Note: Daily panels require multi-day time ranges for meaningful data.",
  "tags": [
    "provisioned",
    "power",
    "historical",
    "victoriametrics"
  ],
  "editable": true,
  "schemaVersion": 41,
  "refresh": "",
  "time": {
    "from": "now-30d",
    "to": "now"
  },
  "timezone": "browser",
  "templating": {
    "list": [
      {
        "name": "host",
        "type": "query",
        "datasource": "VictoriaMetrics (Long-term)",
        "query": "label_values(node_rapl_package_joules_total, source_host)",
        "refresh": 1,
        "includeAll": true,
        "multi": true,
        "current": {
          "selected": true,
          "text": "All",
          "value": "$__all"
        }
      }
    ]
  },
  "panels": [
    {
      "title": "CPU Power Over Time",
      "type": "timeseries",
      "id": 1,
      "gridPos": {
        "h": 10,
        "w": 24,
        "x": 0,
        "y": 0
      },
      "datasource": "VictoriaMetrics (Long-term)",
      "targets": [
        {
          "expr": "sum by (source_host) (rate(node_rapl_package_joules_total{source_host=~\"$host\"}[$__rate_interval]))",
          "legendFormat": "{{source_host}}",
          "refId": "A"
        }
      ],
      "options": {
        "legend": {
          "displayMode": "table",
          "placement": "bottom",
          "showLegend": true,
          "calcs": [
            "mean",
            "max",
            "lastNotNull"
          ]
        },
        "tooltip": {
          "mode": "multi",
          "sort": "desc"
        }
      },
      "fieldConfig": {
        "defaults": {
          "unit": "watt",
          "decimals": 1,
          "custom": {
            "drawStyle": "line",
            "lineInterpolation": "smooth",
            "fillOpacity": 0,
            "gradientMode": "scheme",
            "spanNulls": true,
            "lineWidth": 2
          },
          "color": {
            "mode": "thresholds"
          },
          "thresholds": {
            "mode": "absolute",
            "steps": [
              {
                "color": "green",
                "value": null
              },
              {
                "color": "yellow",
                "value": 35
              },
              {
                "color": "orange",
                "value": 65
              },
              {
                "color": "red",
                "value": 95
              }
            ]
          }
        },
        "overrides": [
          {
            "matcher": {
              "id": "byName",
              "options": "blizzard"
            },
            "properties": [
              {
                "id": "color",
                "value": {
                  "mode": "thresholds"
                }
              },
              {
                "id": "thresholds",
                "value": {
                  "mode": "absolute",
                  "steps": [
                    {
                      "color": "green",
                      "value": null
                    },
                    {
                      "color": "yellow",
                      "value": 35
                    },
                    {
                      "color": "orange",
                      "value": 65
                    },
                    {
                      "color": "red",
                      "value": 95
                    }
                  ]
                }
              }
            ]
          },
          {
            "matcher": {
              "id": "byName",
              "options": "snowfall"
            },
            "properties": [
              {
                "id": "color",
                "value": {
                  "mode": "thresholds"
                }
              },
              {
                "id": "thresholds",
                "value": {
                  "mode": "absolute",
                  "steps": [
                    {
                      "color": "#00FFFF",
                      "value": null
                    },
                    {
                      "color": "#008080",
                      "value": 40
                    },
                    {
                      "color": "#0000FF",
                      "value": 70
                    },
                    {
                      "color": "#800080",
                      "value": 90
                    }
                  ]
                }
              }
            ]
          }
        ]
      }
    },
    {
      "title": "GPU Power Over Time",
      "type": "timeseries",
      "id": 2,
      "gridPos": {
        "h": 10,
        "w": 24,
        "x": 0,
        "y": 10
      },
      "datasource": "VictoriaMetrics (Long-term)",
      "targets": [
        {
          "expr": "sum by (source_host) (node_hwmon_power_average_watt{sensor=\"power1\", source_host=~\"$host\"})",
          "legendFormat": "{{source_host}}",
          "refId": "A"
        }
      ],
      "options": {
        "legend": {
          "displayMode": "table",
          "placement": "bottom",
          "showLegend": true,
          "calcs": [
            "mean",
            "max",
            "lastNotNull"
          ]
        },
        "tooltip": {
          "mode": "multi",
          "sort": "desc"
        }
      },
      "fieldConfig": {
        "defaults": {
          "unit": "watt",
          "decimals": 1,
          "custom": {
            "drawStyle": "line",
            "lineInterpolation": "smooth",
            "fillOpacity": 15,
            "gradientMode": "opacity",
            "spanNulls": true,
            "lineWidth": 2
          },
          "color": {
            "mode": "thresholds"
          },
          "thresholds": {
            "mode": "absolute",
            "steps": [
              {
                "color": "#00FFFF",
                "value": null
              },
              {
                "color": "#008080",
                "value": 30
              },
              {
                "color": "#0000FF",
                "value": 100
              },
              {
                "color": "#800080",
                "value": 200
              }
            ]
          }
        },
        "overrides": []
      }
    },
    {
      "title": "Average Power by Host",
      "description": "Average CPU power aggregated by the selected interval. Use longer time ranges for daily view.",
      "type": "timeseries",
      "id": 3,
      "gridPos": {
        "h": 10,
        "w": 12,
        "x": 0,
        "y": 20
      },
      "datasource": "VictoriaMetrics (Long-term)",
      "targets": [
        {
          "expr": "sum by (source_host) (rate(node_rapl_package_joules_total{source_host=~\"$host\"}[$__rate_interval]))",
          "legendFormat": "{{source_host}}",
          "refId": "A"
        }
      ],
      "options": {
        "legend": {
          "displayMode": "table",
          "placement": "bottom",
          "showLegend": true,
          "calcs": [
            "mean"
          ]
        },
        "tooltip": {
          "mode": "multi",
          "sort": "desc"
        }
      },
      "fieldConfig": {
        "defaults": {
          "unit": "watt",
          "decimals": 1,
          "custom": {
            "drawStyle": "bars",
            "barAlignment": 0,
            "fillOpacity": 70,
            "lineWidth": 0,
            "pointSize": 5,
            "showPoints": "never"
          },
          "color": {
            "mode": "palette-classic"
          }
        },
        "overrides": []
      }
    },
    {
      "title": "Energy Estimate by Host",
      "description": "Estimated energy consumption (power × time). Legend shows totals over selected period.",
      "type": "timeseries",
      "id": 4,
      "gridPos": {
        "h": 10,
        "w": 12,
        "x": 12,
        "y": 20
      },
      "datasource": "VictoriaMetrics (Long-term)",
      "targets": [
        {
          "expr": "sum by (source_host) (rate(node_rapl_package_joules_total{source_host=~\"$host\"}[$__rate_interval])) / 1000",
          "legendFormat": "{{source_host}}",
          "refId": "A"
        }
      ],
      "options": {
        "legend": {
          "displayMode": "table",
          "placement": "bottom",
          "showLegend": true,
          "calcs": [
            "mean",
            "sum"
          ]
        },
        "tooltip": {
          "mode": "multi",
          "sort": "desc"
        }
      },
      "fieldConfig": {
        "defaults": {
          "unit": "kwatt",
          "decimals": 3,
          "custom": {
            "drawStyle": "bars",
            "barAlignment": 0,
            "fillOpacity": 70,
            "lineWidth": 0,
            "pointSize": 5,
            "showPoints": "never"
          },
          "color": {
            "mode": "palette-classic"
          }
        },
        "overrides": []
      }
    },
    {
      "title": "Electricity Price History (NOK/kWh)",
      "type": "timeseries",
      "id": 5,
      "gridPos": {
        "h": 8,
        "w": 24,
        "x": 0,
        "y": 30
      },
      "datasource": "VictoriaMetrics (Long-term)",
      "targets": [
        {
          "expr": "max(electricity_price_nok_per_kwh{tax=\"incl_mva\"})",
          "legendFormat": "Price (incl. MVA)",
          "refId": "A"
        }
      ],
      "options": {
        "legend": {
          "displayMode": "table",
          "placement": "bottom",
          "showLegend": true,
          "calcs": [
            "mean",
            "min",
            "max",
            "lastNotNull"
          ]
        },
        "tooltip": {
          "mode": "single",
          "sort": "none"
        }
      },
      "fieldConfig": {
        "defaults": {
          "unit": "NOK/kWh",
          "decimals": 4,
          "custom": {
            "drawStyle": "line",
            "lineInterpolation": "stepAfter",
            "fillOpacity": 15,
            "gradientMode": "scheme",
            "spanNulls": false,
            "lineWidth": 2
          },
          "color": {
            "mode": "thresholds"
          },
          "thresholds": {
            "mode": "absolute",
            "steps": [
              {
                "color": "green",
                "value": null
              },
              {
                "color": "yellow",
                "value": 0.9
              },
              {
                "color": "orange",
                "value": 1.1
              },
              {
                "color": "red",
                "value": 1.2
              }
            ]
          }
        },
        "overrides": []
      }
    },
    {
      "title": "Daily Energy Cost (Actual)",
      "description": "Actual daily energy cost calculated by multiplying hourly power consumption with the electricity price at that hour. Note: This uses instant values multiplied together, assuming price is sampled at similar times.",
      "type": "timeseries",
      "id": 6,
      "gridPos": {
        "h": 10,
        "w": 12,
        "x": 0,
        "y": 38
      },
      "datasource": "VictoriaMetrics (Long-term)",
      "targets": [
        {
          "expr": "sum_over_time((sum by (source_host) (rate(node_rapl_package_joules_total{source_host=~\"$host\"}[1h])) / 1000)[1d:1h]) * scalar(max(electricity_price_nok_per_kwh{tax=\"incl_mva\"}))",
          "legendFormat": "{{source_host}}",
          "refId": "A"
        }
      ],
      "options": {
        "legend": {
          "displayMode": "table",
          "placement": "bottom",
          "showLegend": true,
          "calcs": [
            "sum"
          ]
        },
        "tooltip": {
          "mode": "multi",
          "sort": "desc"
        }
      },
      "fieldConfig": {
        "defaults": {
          "unit": "currencyNOK",
          "decimals": 2,
          "custom": {
            "drawStyle": "bars",
            "fillOpacity": 70,
            "gradientMode": "none"
          },
          "color": {
            "mode": "palette-classic"
          }
        },
        "overrides": [
          {
            "matcher": {
              "id": "byFrameRefID",
              "options": "A"
            },
            "properties": [
              {
                "id": "displayName",
                "value": "${__field.labels.source_host}"
              }
            ]
          }
        ]
      }
    },
    {
      "title": "Hourly Cost Over Time",
      "description": "Cost rate (NOK/hour) based on actual power consumption and electricity price",
      "type": "timeseries",
      "id": 7,
      "gridPos": {
        "h": 10,
        "w": 12,
        "x": 12,
        "y": 38
      },
      "datasource": "VictoriaMetrics (Long-term)",
      "targets": [
        {
          "expr": "sum by (source_host) (rate(node_rapl_package_joules_total{source_host=~\"$host\"}[$__rate_interval])) / 1000 * scalar(max(electricity_price_nok_per_kwh{tax=\"incl_mva\"}))",
          "legendFormat": "{{source_host}}",
          "refId": "A"
        }
      ],
      "options": {
        "legend": {
          "displayMode": "table",
          "placement": "bottom",
          "showLegend": true,
          "calcs": [
            "mean",
            "sum"
          ]
        },
        "tooltip": {
          "mode": "multi",
          "sort": "desc"
        }
      },
      "fieldConfig": {
        "defaults": {
          "unit": "currencyNOK",
          "decimals": 3,
          "custom": {
            "drawStyle": "line",
            "lineInterpolation": "stepAfter",
            "fillOpacity": 0,
            "gradientMode": "scheme",
            "spanNulls": false,
            "lineWidth": 2
          },
          "color": {
            "mode": "thresholds"
          },
          "thresholds": {
            "mode": "absolute",
            "steps": [
              {
                "color": "green",
                "value": null
              },
              {
                "color": "yellow",
                "value": 0.03
              },
              {
                "color": "orange",
                "value": 0.05
              },
              {
                "color": "red",
                "value": 0.08
              }
            ]
          }
        },
        "overrides": [
          {
            "matcher": {
              "id": "byFrameRefID",
              "options": "A"
            },
            "properties": [
              {
                "id": "displayName",
                "value": "${__field.labels.source_host}"
              }
            ]
          },
          {
            "matcher": {
              "id": "byName",
              "options": "blizzard"
            },
            "properties": [
              {
                "id": "color",
                "value": {
                  "mode": "thresholds"
                }
              },
              {
                "id": "thresholds",
                "value": {
                  "mode": "absolute",
                  "steps": [
                    {
                      "color": "green",
                      "value": null
                    },
                    {
                      "color": "yellow",
                      "value": 0.03
                    },
                    {
                      "color": "orange",
                      "value": 0.05
                    },
                    {
                      "color": "red",
                      "value": 0.08
                    }
                  ]
                }
              }
            ]
          },
          {
            "matcher": {
              "id": "byName",
              "options": "snowfall"
            },
            "properties": [
              {
                "id": "color",
                "value": {
                  "mode": "thresholds"
                }
              },
              {
                "id": "thresholds",
                "value": {
                  "mode": "absolute",
                  "steps": [
                    {
                      "color": "#00FFFF",
                      "value": null
                    },
                    {
                      "color": "#008080",
                      "value": 0.03
                    },
                    {
                      "color": "#0000FF",
                      "value": 0.05
                    },
                    {
                      "color": "#800080",
                      "value": 0.08
                    }
                  ]
                }
              }
            ]
          }
        ]
      }
    },
    {
      "title": "Cumulative Cost (Selected Period)",
      "description": "Total accumulated cost over the selected time period",
      "type": "stat",
      "id": 8,
      "gridPos": {
        "h": 5,
        "w": 8,
        "x": 0,
        "y": 48
      },
      "datasource": "VictoriaMetrics (Long-term)",
      "targets": [
        {
          "expr": "sum(sum_over_time((sum by (source_host) (rate(node_rapl_package_joules_total{source_host=~\"$host\"}[1h])) / 1000)[$__range:1h])) * scalar(max(electricity_price_nok_per_kwh{tax=\"incl_mva\"}))",
          "legendFormat": "Total Cost",
          "refId": "A"
        }
      ],
      "options": {
        "reduceOptions": {
          "values": false,
          "calcs": [
            "lastNotNull"
          ],
          "fields": ""
        },
        "orientation": "auto",
        "textMode": "auto",
        "colorMode": "value",
        "graphMode": "none",
        "justifyMode": "auto"
      },
      "fieldConfig": {
        "defaults": {
          "unit": "currencyNOK",
          "decimals": 2,
          "color": {
            "mode": "thresholds"
          },
          "thresholds": {
            "mode": "absolute",
            "steps": [
              {
                "color": "green",
                "value": null
              },
              {
                "color": "yellow",
                "value": 50
              },
              {
                "color": "red",
                "value": 100
              }
            ]
          }
        },
        "overrides": []
      }
    },
    {
      "title": "Average Price (Selected Period)",
      "description": "Average electricity price over the selected time period",
      "type": "stat",
      "id": 9,
      "gridPos": {
        "h": 5,
        "w": 8,
        "x": 8,
        "y": 48
      },
      "datasource": "VictoriaMetrics (Long-term)",
      "targets": [
        {
          "expr": "avg_over_time(max(electricity_price_nok_per_kwh{tax=\"incl_mva\"})[$__range])",
          "legendFormat": "Avg Price",
          "refId": "A"
        }
      ],
      "options": {
        "reduceOptions": {
          "values": false,
          "calcs": [
            "lastNotNull"
          ],
          "fields": ""
        },
        "orientation": "auto",
        "textMode": "auto",
        "colorMode": "value",
        "graphMode": "none",
        "justifyMode": "auto"
      },
      "fieldConfig": {
        "defaults": {
          "unit": "currencyNOK",
          "decimals": 3,
          "displayName": "Avg NOK/kWh",
          "color": {
            "mode": "thresholds"
          },
          "thresholds": {
            "mode": "absolute",
            "steps": [
              {
                "color": "green",
                "value": null
              },
              {
                "color": "yellow",
                "value": 0.5
              },
              {
                "color": "red",
                "value": 1.0
              }
            ]
          }
        },
        "overrides": []
      }
    },
    {
      "title": "Total Energy (Selected Period)",
      "description": "Total energy consumed over the selected time period",
      "type": "stat",
      "id": 10,
      "gridPos": {
        "h": 5,
        "w": 8,
        "x": 16,
        "y": 48
      },
      "datasource": "VictoriaMetrics (Long-term)",
      "targets": [
        {
          "expr": "sum(\n  sum_over_time(\n    (sum by (source_host) (rate(node_rapl_package_joules_total{source_host=~\"$host\"}[1h])) / 1000)[$__range:1h]\n  )\n)",
          "legendFormat": "Total kWh",
          "refId": "A"
        }
      ],
      "options": {
        "reduceOptions": {
          "values": false,
          "calcs": [
            "lastNotNull"
          ],
          "fields": ""
        },
        "orientation": "auto",
        "textMode": "auto",
        "colorMode": "value",
        "graphMode": "none",
        "justifyMode": "auto"
      },
      "fieldConfig": {
        "defaults": {
          "unit": "kwatth",
          "decimals": 2,
          "displayName": "Total kWh",
          "color": {
            "mode": "thresholds"
          },
          "thresholds": {
            "mode": "absolute",
            "steps": [
              {
                "color": "green",
                "value": null
              },
              {
                "color": "yellow",
                "value": 50
              },
              {
                "color": "red",
                "value": 100
              }
            ]
          }
        },
        "overrides": []
      }
    }
  ],
  "annotations": {
    "list": []
  },
  "links": []
}
